LICENSE
MANIFEST.in
README.rst
setup.py
logwatch/__init__.py
logwatch/mailer.py
logwatch/tail.py
logwatch/watcher.py
logwatch.egg-info/PKG-INFO
logwatch.egg-info/SOURCES.txt
logwatch.egg-info/dependency_links.txt
logwatch.egg-info/entry_points.txt
logwatch.egg-info/requires.txt
logwatch.egg-info/top_level.txt